{
  "source": "/home/maxime/AFRILANG/examples/vizultra_demo.afr",
  "variables": [
    {"name":"grid","type":"list number","scope":"global"},
    {"name":"w","type":"number","scope":"global"},
    {"name":"ok3","type":"bool","scope":"global"},
    {"name":"ok5","type":"bool","scope":"global"},
    {"name":"ok4","type":"bool","scope":"global"},
    {"name":"ok2","type":"bool","scope":"global"},
    {"name":"ok1","type":"bool","scope":"global"},
    {"name":"h","type":"number","scope":"global"},
    {"name":"xs","type":"list number","scope":"global"},
    {"name":"ys","type":"list number","scope":"global"},
    {"name":"path","type":"text","scope":"writeLineChart"},
    {"name":"ys","type":"list number","scope":"writeLineChart"},
    {"name":"width","type":"number","scope":"writeLineChart"},
    {"name":"height","type":"number","scope":"writeLineChart"},
    {"name":"path","type":"text","scope":"writeBarChart"},
    {"name":"ys","type":"list number","scope":"writeBarChart"},
    {"name":"width","type":"number","scope":"writeBarChart"},
    {"name":"height","type":"number","scope":"writeBarChart"},
    {"name":"path","type":"text","scope":"writeScatter"},
    {"name":"xs","type":"list number","scope":"writeScatter"},
    {"name":"ys","type":"list number","scope":"writeScatter"},
    {"name":"width","type":"number","scope":"writeScatter"},
    {"name":"height","type":"number","scope":"writeScatter"},
    {"name":"path","type":"text","scope":"writeCsv"},
    {"name":"ys","type":"list number","scope":"writeCsv"},
    {"name":"path","type":"text","scope":"writeHeatmap"},
    {"name":"grid","type":"list number","scope":"writeHeatmap"},
    {"name":"w","type":"number","scope":"writeHeatmap"},
    {"name":"h","type":"number","scope":"writeHeatmap"},
    {"name":"width","type":"number","scope":"writeHeatmap"},
    {"name":"height","type":"number","scope":"writeHeatmap"}
  ]
}
